pyreqif/__init__.py
pyreqif/extractOleData.py
pyreqif/html.py
pyreqif/ole2rtf.py
pyreqif/pyreqif.py
pyreqif/reqif.py
pyreqif/xlsx.py
pyreqif-0.1.data/scripts/reqif2html.py
pyreqif-0.1.data/scripts/reqif2xlsx.py
pyreqif-0.1.dist-info/DESCRIPTION.rst
pyreqif-0.1.dist-info/METADATA
pyreqif-0.1.dist-info/RECORD
pyreqif-0.1.dist-info/WHEEL
pyreqif-0.1.dist-info/metadata.json
pyreqif-0.1.dist-info/top_level.txt
